Workbook

Sheet Quick Check
A1: CAN I BUY IT? — CORRECTED
A3: Item name | B3: Tech item | C3: Description only; it does not alter the calculation.
A4: Full upfront cost | B4: 4000 | C4: Include tax, delivery, installation, and required accessories.
A5: New recurring monthly cost | B5: 0 | C5: Subscriptions, maintenance, consumables, insurance, etc.
A7: RESULT
A8: Input check | B8: =IF(OR('Budget Setup'!B26<>"VALID",B4="",NOT(ISNUMBER(B4)),B4<=0,B5="",NOT(ISNUMBER(B5)),B5<0),"INVALID","VALID") | C8: A decision appears only after all inputs are valid.
A9: Current safe-zone status | B9: =IF('Budget Setup'!B26<>"VALID","INVALID INPUT",IF('Budget Setup'!B21=0,"IN SAFE ZONE","NEED ₹"&TEXT('Budget Setup'!B21,"#,##0.00")&" MORE")) | C9: Uses the same reserved-cash definition as every other result.
A10: Decision | B10: =IF(OR(B4="",NOT(ISNUMBER(B4)),B4<=0),"ENTER A VALID PRICE",IF(OR(B5="",NOT(ISNUMBER(B5)),B5<0,'Budget Setup'!B26<>"VALID"),"INVALID INPUT",IF('Budget Setup'!B22>0,"URGENT CASH SHORTFALL",IF(AND(B5>0,B5>'Budget Setup'!B17),"NOT AFFORDABLE: RECURRING COST",IF(B4<=MAX(0,'Budget Setup'!B5-'Budget Setup'!B20),"BUY NOW",IF('Budget Setup'!B17<=0,"NOT AFFORDABLE WITH CURRENT BUDGET","WAIT UNTIL "&TEXT(B17,"dd-mmm-yyyy"))))))) | C10: Decision order prevents contradictory results.
A11: Minimum safety buffer | B11: ='Budget Setup'!B19 | C11: Commitments × buffer months.
A12: Total reserved cash | B12: ='Budget Setup'!B20 | C12: Buffer plus costs due before next income.
A13: Money needed for safe zone | B13: ='Budget Setup'!B21 | C13: Gap before considering this item.
A14: Estimated safe-zone date | B14: ='Budget Setup'!B24 | C14: Separate from the purchase date.
A15: Safe spending money now | B15: ='Budget Setup'!B25 | C15: Maximum optional cash available now.
A16: Total money still needed | B16: =IF(OR(B4="",NOT(ISNUMBER(B4)),B4<=0),"",MAX(0,'Budget Setup'!B20+B4-'Budget Setup'!B5)) | C16: Includes the full reserve deficit and item price.
A17: Earliest safe purchase date | B17: =IF(B8<>"VALID","",IF(B4<='Budget Setup'!B25,'Budget Setup'!B3,IF('Budget Setup'!B17<=0,"",DATE(YEAR(EDATE('Budget Setup'!B7,ROUNDUP(B16/'Budget Setup'!B17,0)-1)),MONTH(EDATE('Budget Setup'!B7,ROUNDUP(B16/'Budget Setup'!B17,0)-1)),MIN('Budget Setup'!B8,DAY(EOMONTH(EDATE('Budget Setup'!B7,ROUNDUP(B16/'Budget Setup'!B17,0)-1),0))))))) | C17: Cycle 1 equals the next confirmed income date.
A18: Months of saving required | B18: =IF(B8<>"VALID","",IF(B16=0,0,IF('Budget Setup'!B17<=0,"N/A",ROUNDUP(B16/'Budget Setup'!B17,0)))) | C18: Whole monthly saving cycles.
A19: Monthly surplus after purchase | B19: =IF(B8<>"VALID","",'Budget Setup'!B17-B5) | C19: Must not be negative for a recurring-cost purchase.
A20: Urgent shortfall before income | B20: ='Budget Setup'!B22 | C20: Resolve this before optional purchases.

Sheet Budget Setup
A1: BUDGET SETUP & SAFE ZONE
A3: As-of date | B3: 46302 | C3: Date when the cleared balance was checked.
A4: Currency | B4: INR | C4: All monetary inputs must use the same currency.
A5: Cleared spendable balance | B5: 3000 | C5: Exclude credit limits, pending deposits, investments, and protected/earmarked savings.
A6: Average monthly take-home income | B6: 8000 | C6: For irregular income, use a conservative amount and update frequently.
A7: Next income date — not yet in balance | B7: 46327 | C7: Use the next confirmed income date. If today's salary is already in the balance, enter the following payday.
A8: Regular monthly income day | B8: 1 | C8: 1–31. Short months automatically use their final calendar day.
A9: Loan/debt payments | B9: 1000 | C9: Required monthly payment.
A10: Untouchable investment contribution | B10: 400 | C10: Keep only if this contribution must not be paused.
A11: Transport / petrol | B11: 2000 | C11: Normal required monthly amount.
A12: Other essential monthly costs | B12: 0 | C12: Food, housing, medical, education, subscriptions, etc., if personally paid.
A13: Unavoidable expenses due before next income | B13: 0 | C13: Only confirmed costs due before the next income date; update after payment.
A15: CALCULATED MONTHLY POSITION
A16: Total monthly commitments | B16: =SUM(B9:B12) | C16: Required monthly costs protected by the model.
A17: Monthly surplus | B17: =B6-B16 | C17: Income remaining after commitments.
A18: Safety buffer (months) — EDIT | B18: 6 | C18: Examples: 0.5 = half month, 1 = one month, 6 = six months.
A19: Minimum safety buffer | B19: =B16*B18 | C19: Monthly commitments multiplied by buffer months.
A20: Total reserved cash | B20: =B19+B13 | C20: Safety buffer plus unavoidable costs due before next income.
A21: Money needed to enter safe zone | B21: =MAX(0,B20-B5) | C21: How much more cash is needed to cover all reserved cash.
A22: Urgent shortfall before next income | B22: =MAX(0,B13-B5) | C22: If positive, upcoming obligations exceed current spendable cash.
A23: Months until safe zone | B23: =IF(B26<>"VALID","",IF(B21=0,0,IF(B17<=0,"N/A",ROUNDUP(B21/B17,0)))) | C23: Whole monthly saving cycles required.
A24: Estimated safe-zone date | B24: =IF(B26<>"VALID","",IF(B21=0,B3,IF(B17<=0,"",DATE(YEAR(EDATE(B7,B23-1)),MONTH(EDATE(B7,B23-1)),MIN(B8,DAY(EOMONTH(EDATE(B7,B23-1),0))))))) | C24: Cycle 1 is exactly the next income date.
A25: Safe spending money now | B25: =MAX(0,B5-B20) | C25: Maximum optional spending without breaking the reserve.
A26: Input status | B26: =IF(AND(ISNUMBER(B3),B4<>"",ISNUMBER(B5),ISNUMBER(B6),B6>=0,ISNUMBER(B7),B7>=B3,ISNUMBER(B8),B8>=1,B8<=31,COUNT(B9:B13)=5,MIN(B9:B13)>=0,ISNUMBER(B18),B18>=0,B18<=120),"VALID","INVALID INPUT") | C26: Fix invalid or missing values before trusting decisions.
A27: Data freshness | B27: =IF(TODAY()-B3>7,"STALE — UPDATE BALANCE","CURRENT") | C27: Update the cleared balance after every income, expense, or purchase.

Sheet Purchase Plan
A1: COMBINED PURCHASE PLAN
A2: Select Yes for every item you intend to buy together. The result checks the combined cost, preventing repeated-spending errors.
A3: Include? | B3: Item | C3: Full upfront cost | D3: New monthly cost | E3: Input status | F3: Notes
A4: No | E4: =IF(A4<>"Yes","NOT SELECTED",IF(OR(B4="",C4="",NOT(ISNUMBER(C4)),C4<=0,D4="",NOT(ISNUMBER(D4)),D4<0),"INVALID","VALID"))
A5: No | E5: =IF(A5<>"Yes","NOT SELECTED",IF(OR(B5="",C5="",NOT(ISNUMBER(C5)),C5<=0,D5="",NOT(ISNUMBER(D5)),D5<0),"INVALID","VALID"))
A6: No | E6: =IF(A6<>"Yes","NOT SELECTED",IF(OR(B6="",C6="",NOT(ISNUMBER(C6)),C6<=0,D6="",NOT(ISNUMBER(D6)),D6<0),"INVALID","VALID"))
A7: No | E7: =IF(A7<>"Yes","NOT SELECTED",IF(OR(B7="",C7="",NOT(ISNUMBER(C7)),C7<=0,D7="",NOT(ISNUMBER(D7)),D7<0),"INVALID","VALID"))
A8: No | E8: =IF(A8<>"Yes","NOT SELECTED",IF(OR(B8="",C8="",NOT(ISNUMBER(C8)),C8<=0,D8="",NOT(ISNUMBER(D8)),D8<0),"INVALID","VALID"))
A9: No | E9: =IF(A9<>"Yes","NOT SELECTED",IF(OR(B9="",C9="",NOT(ISNUMBER(C9)),C9<=0,D9="",NOT(ISNUMBER(D9)),D9<0),"INVALID","VALID"))
A10: No | E10: =IF(A10<>"Yes","NOT SELECTED",IF(OR(B10="",C10="",NOT(ISNUMBER(C10)),C10<=0,D10="",NOT(ISNUMBER(D10)),D10<0),"INVALID","VALID"))
A11: No | E11: =IF(A11<>"Yes","NOT SELECTED",IF(OR(B11="",C11="",NOT(ISNUMBER(C11)),C11<=0,D11="",NOT(ISNUMBER(D11)),D11<0),"INVALID","VALID"))
A12: No | E12: =IF(A12<>"Yes","NOT SELECTED",IF(OR(B12="",C12="",NOT(ISNUMBER(C12)),C12<=0,D12="",NOT(ISNUMBER(D12)),D12<0),"INVALID","VALID"))
A13: No | E13: =IF(A13<>"Yes","NOT SELECTED",IF(OR(B13="",C13="",NOT(ISNUMBER(C13)),C13<=0,D13="",NOT(ISNUMBER(D13)),D13<0),"INVALID","VALID"))
A14: No | E14: =IF(A14<>"Yes","NOT SELECTED",IF(OR(B14="",C14="",NOT(ISNUMBER(C14)),C14<=0,D14="",NOT(ISNUMBER(D14)),D14<0),"INVALID","VALID"))
A15: No | E15: =IF(A15<>"Yes","NOT SELECTED",IF(OR(B15="",C15="",NOT(ISNUMBER(C15)),C15<=0,D15="",NOT(ISNUMBER(D15)),D15<0),"INVALID","VALID"))
... A23: No | E23: =IF(A23<>"Yes","NOT SELECTED",IF(OR(B23="",C23="",NOT(ISNUMBER(C23)),C23<=0,D23="",NOT(ISNUMBER(D23)),D23<0),"INVALID","VALID"))
A25: COMBINED RESULT
A26: Selected item count | B26: =COUNTIF(A4:A23,"Yes")
A27: Selected upfront total | B27: =SUMIF(A4:A23,"Yes",C4:C23)
A28: Selected recurring monthly total | B28: =SUMIF(A4:A23,"Yes",D4:D23)
A29: Total cash required | B29: ='Budget Setup'!B20+B27
A30: Money still needed | B30: =MAX(0,B29-'Budget Setup'!B5)
A31: Months to wait | B31: =IF(B26=0,"",IF(B30=0,0,IF('Budget Setup'!B17<=0,"N/A",ROUNDUP(B30/'Budget Setup'!B17,0))))
A32: Earliest combined purchase date | B32: =IF(B26=0,"",IF(B30=0,'Budget Setup'!B3,IF('Budget Setup'!B17<=0,"",DATE(YEAR(EDATE('Budget Setup'!B7,B31-1)),MONTH(EDATE('Budget Setup'!B7,B31-1)),MIN('Budget Setup'!B8,DAY(EOMONTH(EDATE('Budget Setup'!B7,B31-1),0)))))))
A33: Combined decision | B33: =IF(B26=0,"SELECT ITEMS",IF(COUNTIFS(A4:A23,"Yes",E4:E23,"<>VALID")>0,"INVALID SELECTED ITEM",IF('Budget Setup'!B26<>"VALID","INVALID BUDGET INPUT",IF('Budget Setup'!B22>0,"URGENT CASH SHORTFALL",IF(AND(B28>0,B28>'Budget Setup'!B17),"NOT AFFORDABLE: RECURRING COST",IF(B27<='Budget Setup'!B25,"BUY NOW",IF('Budget Setup'!B17<=0,"NOT AFFORDABLE WITH CURRENT BUDGET","WAIT UNTIL "&TEXT(B32,"dd-mmm-yyyy"))))))))

Sheet Validation Tests
A1: BUILT-IN MODEL VALIDATION
A2: Case | B2: Balance | C2: Income | D2: Commitments | E2: Upcoming | F2: Buffer | G2: Price | H2: Recurring | I2: Expected | J2: Calculated | K2: Status
A3: Normal buy now | B3: 10000 | C3: 5000 | D3: 3000 | E3: 100 | F3: 2 | G3: 1000 | H3: 0 | I3: BUY NOW | J3: =IF(OR(C3<0,D3<0,E3<0,F3<0,G3<0,H3<0),"INVALID INPUT",IF(G3=0,"ENTER A VALID PRICE",IF(MAX(0,E3-B3)>0,"URGENT CASH SHORTFALL",IF(AND(H3>0,H3>C3-D3),"NOT AFFORDABLE: RECURRING COST",IF(G3<=MAX(0,B3-(D3*F3+E3)),"BUY NOW",IF(C3-D3<=0,"NOT AFFORDABLE","WAIT")))))) | K3: =IF(I3=J3,"PASS","FAIL")
A4: Needs saving | B4: 1000 | C4: 5000 | D4: 3000 | E4: 500 | F4: 2 | G4: 2500 | H4: 0 | I4: WAIT | J4: =IF(OR(C4<0,D4<0,E4<0,F4<0,G4<0,H4<0),"INVALID INPUT",IF(G4=0,"ENTER A VALID PRICE",IF(MAX(0,E4-B4)>0,"URGENT CASH SHORTFALL",IF(AND(H4>0,H4>C4-D4),"NOT AFFORDABLE: RECURRING COST",IF(G4<=MAX(0,B4-(D4*F4+E4)),"BUY NOW",IF(C4-D4<=0,"NOT AFFORDABLE","WAIT")))))) | K4: =IF(I4=J4,"PASS","FAIL")
A5: Zero price | B5: 1000 | C5: 3000 | D5: 2000 | E5: 0 | F5: 1 | G5: 0 | H5: 0 | I5: ENTER A VALID PRICE | J5: =IF(OR(C5<0,D5<0,E5<0,F5<0,G5<0,H5<0),"INVALID INPUT",IF(G5=0,"ENTER A VALID PRICE",IF(MAX(0,E5-B5)>0,"URGENT CASH SHORTFALL",IF(AND(H5>0,H5>C5-D5),"NOT AFFORDABLE: RECURRING COST",IF(G5<=MAX(0,B5-(D5*F5+E5)),"BUY NOW",IF(C5-D5<=0,"NOT AFFORDABLE","WAIT")))))) | K5: =IF(I5=J5,"PASS","FAIL")
A6: Negative price | B6: 1000 | C6: 3000 | D6: 2000 | E6: 0 | F6: 1 | G6: -1 | H6: 0 | I6: INVALID INPUT | J6: =IF(OR(C6<0,D6<0,E6<0,F6<0,G6<0,H6<0),"INVALID INPUT",IF(G6=0,"ENTER A VALID PRICE",IF(MAX(0,E6-B6)>0,"URGENT CASH SHORTFALL",IF(AND(H6>0,H6>C6-D6),"NOT AFFORDABLE: RECURRING COST",IF(G6<=MAX(0,B6-(D6*F6+E6)),"BUY NOW",IF(C6-D6<=0,"NOT AFFORDABLE","WAIT")))))) | K6: =IF(I6=J6,"PASS","FAIL")
A7: Negative buffer | B7: 0 | C7: 3000 | D7: 2000 | E7: 0 | F7: -1 | G7: 500 | H7: 0 | I7: INVALID INPUT | J7: =IF(OR(C7<0,D7<0,E7<0,F7<0,G7<0,H7<0),"INVALID INPUT",IF(G7=0,"ENTER A VALID PRICE",IF(MAX(0,E7-B7)>0,"URGENT CASH SHORTFALL",IF(AND(H7>0,H7>C7-D7),"NOT AFFORDABLE: RECURRING COST",IF(G7<=MAX(0,B7-(D7*F7+E7)),"BUY NOW",IF(C7-D7<=0,"NOT AFFORDABLE","WAIT")))))) | K7: =IF(I7=J7,"PASS","FAIL")
A8: Negative commitments | B8: 0 | C8: 3000 | D8: -1000 | E8: 0 | F8: 1 | G8: 500 | H8: 0 | I8: INVALID INPUT | J8: =IF(OR(C8<0,D8<0,E8<0,F8<0,G8<0,H8<0),"INVALID INPUT",IF(G8=0,"ENTER A VALID PRICE",IF(MAX(0,E8-B8)>0,"URGENT CASH SHORTFALL",IF(AND(H8>0,H8>C8-D8),"NOT AFFORDABLE: RECURRING COST",IF(G8<=MAX(0,B8-(D8*F8+E8)),"BUY NOW",IF(C8-D8<=0,"NOT AFFORDABLE","WAIT")))))) | K8: =IF(I8=J8,"PASS","FAIL")
A9: Zero surplus but cash available | B9: 10000 | C9: 1000 | D9: 1000 | E9: 0 | F9: 6 | G9: 500 | H9: 0 | I9: BUY NOW | J9: =IF(OR(C9<0,D9<0,E9<0,F9<0,G9<0,H9<0),"INVALID INPUT",IF(G9=0,"ENTER A VALID PRICE",IF(MAX(0,E9-B9)>0,"URGENT CASH SHORTFALL",IF(AND(H9>0,H9>C9-D9),"NOT AFFORDABLE: RECURRING COST",IF(G9<=MAX(0,B9-(D9*F9+E9)),"BUY NOW",IF(C9-D9<=0,"NOT AFFORDABLE","WAIT")))))) | K9: =IF(I9=J9,"PASS","FAIL")
A10: Zero surplus and shortage | B10: 6000 | C10: 1000 | D10: 1000 | E10: 0 | F10: 6 | G10: 500 | H10: 0 | I10: NOT AFFORDABLE | J10: =IF(OR(C10<0,D10<0,E10<0,F10<0,G10<0,H10<0),"INVALID INPUT",IF(G10=0,"ENTER A VALID PRICE",IF(MAX(0,E10-B10)>0,"URGENT CASH SHORTFALL",IF(AND(H10>0,H10>C10-D10),"NOT AFFORDABLE: RECURRING COST",IF(G10<=MAX(0,B10-(D10*F10+E10)),"BUY NOW",IF(C10-D10<=0,"NOT AFFORDABLE","WAIT")))))) | K10: =IF(I10=J10,"PASS","FAIL")
A11: Urgent pre-income shortage | B11: 100 | C11: 1000 | D11: 800 | E11: 500 | F11: 1 | G11: 100 | H11: 0 | I11: URGENT CASH SHORTFALL | J11: =IF(OR(C11<0,D11<0,E11<0,F11<0,G11<0,H11<0),"INVALID INPUT",IF(G11=0,"ENTER A VALID PRICE",IF(MAX(0,E11-B11)>0,"URGENT CASH SHORTFALL",IF(AND(H11>0,H11>C11-D11),"NOT AFFORDABLE: RECURRING COST",IF(G11<=MAX(0,B11-(D11*F11+E11)),"BUY NOW",IF(C11-D11<=0,"NOT AFFORDABLE","WAIT")))))) | K11: =IF(I11=J11,"PASS","FAIL")
A12: Recurring cost too high | B12: 30000 | C12: 8000 | D12: 3400 | E12: 0 | F12: 6 | G12: 1000 | H12: 5000 | I12: NOT AFFORDABLE: RECURRING COST | J12: =IF(OR(C12<0,D12<0,E12<0,F12<0,G12<0,H12<0),"INVALID INPUT",IF(G12=0,"ENTER A VALID PRICE",IF(MAX(0,E12-B12)>0,"URGENT CASH SHORTFALL",IF(AND(H12>0,H12>C12-D12),"NOT AFFORDABLE: RECURRING COST",IF(G12<=MAX(0,B12-(D12*F12+E12)),"BUY NOW",IF(C12-D12<=0,"NOT AFFORDABLE","WAIT")))))) | K12: =IF(I12=J12,"PASS","FAIL")
A13: Exact boundary | B13: 24400 | C13: 8000 | D13: 3400 | E13: 0 | F13: 6 | G13: 4000 | H13: 0 | I13: BUY NOW | J13: =IF(OR(C13<0,D13<0,E13<0,F13<0,G13<0,H13<0),"INVALID INPUT",IF(G13=0,"ENTER A VALID PRICE",IF(MAX(0,E13-B13)>0,"URGENT CASH SHORTFALL",IF(AND(H13>0,H13>C13-D13),"NOT AFFORDABLE: RECURRING COST",IF(G13<=MAX(0,B13-(D13*F13+E13)),"BUY NOW",IF(C13-D13<=0,"NOT AFFORDABLE","WAIT")))))) | K13: =IF(I13=J13,"PASS","FAIL")
A14: Fractional buffer | B14: 1000 | C14: 4000 | D14: 2500 | E14: 250 | F14: 0.5 | G14: 100 | H14: 0 | I14: WAIT | J14: =IF(OR(C14<0,D14<0,E14<0,F14<0,G14<0,H14<0),"INVALID INPUT",IF(G14=0,"ENTER A VALID PRICE",IF(MAX(0,E14-B14)>0,"URGENT CASH SHORTFALL",IF(AND(H14>0,H14>C14-D14),"NOT AFFORDABLE: RECURRING COST",IF(G14<=MAX(0,B14-(D14*F14+E14)),"BUY NOW",IF(C14-D14<=0,"NOT AFFORDABLE","WAIT")))))) | K14: =IF(I14=J14,"PASS","FAIL")
A15: Negative balance | B15: -100 | C15: 3000 | D15: 2000 | E15: 0 | F15: 1 | G15: 500 | H15: 0 | I15: WAIT | J15: =IF(OR(C15<0,D15<0,E15<0,F15<0,G15<0,H15<0),"INVALID INPUT",IF(G15=0,"ENTER A VALID PRICE",IF(MAX(0,E15-B15)>0,"URGENT CASH SHORTFALL",IF(AND(H15>0,H15>C15-D15),"NOT AFFORDABLE: RECURRING COST",IF(G15<=MAX(0,B15-(D15*F15+E15)),"BUY NOW",IF(C15-D15<=0,"NOT AFFORDABLE","WAIT")))))) | K15: =IF(I15=J15,"PASS","FAIL")

Sheet Guide
A1: HOW TO USE THE CALCULATOR
A3: 1 | B3: Update Budget Setup | C3: Enter only cleared spendable cash. Exclude protected savings, credit limits, and pending deposits.
A4: 2 | B4: Use the next confirmed income date | C4: The date must represent income not already included in the balance. The calculator assumes a regular monthly cycle.
A5: 3 | B5: Record near-term obligations | C5: Enter confirmed unavoidable expenses due before the next income. A positive urgent-shortfall result blocks optional purchases.
A6: 4 | B6: Choose a buffer | C6: Set the number of months of commitments to protect. All safe-zone and purchase calculations use the same reserve definition.
A7: 5 | B7: Check one purchase | C7: In Quick Check, enter the complete upfront cost and any new recurring monthly cost.
A8: 6 | B8: Plan several purchases | C8: In Purchase Plan, select Yes for items intended together. The sheet evaluates their combined cost rather than approving each independently.
A9: 7 | B9: Recalculate after every transaction | C9: A BUY NOW result is valid once against the recorded balance. Update the balance after buying, receiving income, paying an expense, or receiving a refund.
A10: 8 | B10: Know the scope | C10: This version models regular monthly income. For irregular, weekly, biweekly, or seasonal income, use a conservative monthly figure and do not rely on distant dates.
B13: Decision order | C13: INVALID INPUT → URGENT CASH SHORTFALL → recurring-cost check → BUY NOW → NOT AFFORDABLE → WAIT UNTIL.
B14: Disclaimer | C14: This is a conservative planning tool, not professional financial advice. Dates depend on accurate, current inputs.
