Workbook

Sheet Quick Check
A1: CAN I BUY IT?
A3: Item name | B3: Example: skincare / snack / tech
A4: Category | B4: Tech
A5: Full price | B5: 0
A6: Priority | B6: Optional
A8: RESULT
A9: Decision | B9: =IF(B5<=0,"ENTER A PRICE",IF(B5<='My Budget'!B17,"BUY NOW",IF('My Budget'!B16<=0,"NOT AFFORDABLE WITH CURRENT BUDGET","WAIT UNTIL "&TEXT(B17,"dd-mmm-yyyy")))) -> ENTER A PRICE
A10: Current safe-zone status | B10: ='My Budget'!B23 -> IN SAFE ZONE
A11: Estimated date you enter safe zone | B11: ='My Budget'!B25 -> 46302
A12: Required minimum safe balance | B12: ='My Budget'!B15 -> 0
A13: Money needed to enter safe zone | B13: ='My Budget'!B22 -> 0
A14: Safe maximum purchase now | B14: ='My Budget'!B17 -> 0
A15: Total money still needed (buffer + item) | B15: =MAX(0,'My Budget'!B15+'My Budget'!B12+B5-'My Budget'!B4) -> 0
A16: Months of saving needed | B16: =IF(B5<=0,"",IF(B5<=B14,0,IF('My Budget'!B16<=0,"N/A",ROUNDUP(B15/'My Budget'!B16,0))))
A17: Estimated safe purchase date | B17: =IF(B5<=0,"",IF(B5<=B14,'My Budget'!B3,IF('My Budget'!B16<=0,"",EDATE('My Budget'!B18,B16-1))))
A18: Balance if bought today | B18: ='My Budget'!B4-B5 -> 0
A19: Buffer remaining after buying today | B19: =B18-'My Budget'!B15-'My Budget'!B12 -> 0
A20: Price as % of monthly surplus | B20: =IF('My Budget'!B16<=0,"",B5/'My Budget'!B16) -> 0
A22: Rule used | B22: Cash-only. A purchase is safe now only when your customized safety buffer remains intact.

Sheet My Budget
A1: MY MONTHLY MONEY SETUP
E2: Monthly Allocation
A3: As-of date | B3: 46302 | C3: Update this whenever you use the workbook. | E3: Loan | F3: =B8 -> 0
A4: Current bank/cash balance | B4: 0 | C4: Money available right now. | E4: Investment | F4: =B9 -> 0
A5: Monthly take-home income | B5: 8000 | C5: Salary received on the first of each month. | E5: Petrol | F5: =B10 -> 0
A6: Salary day of month | B6: 1 | C6: Use a number from 1 to 28. | E6: Other essentials | F6: =B11 -> 0
E7: Surplus | F7: =MAX(0,B16) -> 8000
A8: Loan payment | B8: 0 | C8: Required monthly payment.
A9: Monthly investment | B9: 0 | C9: Marked untouchable by you.
A10: Petrol / transport | B10: 0 | C10: Your estimated normal monthly requirement.
A11: Other essential expenses | B11: 0 | C11: Add any essential cost not paid by family.
A12: Upcoming unavoidable cost | B12: 0 | C12: One-time amount due before next salary.
A13: Total monthly commitments | B13: =SUM(B8:B11) -> 0 | C13: Loan + investment + petrol + other essentials.
A14: Safety buffer (months) — EDIT THIS | B14: 0 | C14: Customizable: 1 means one month, 0.5 means half a month, 2 means two months.
A15: Required safety buffer | B15: =B13*B14 -> 0 | C15: Minimum balance the calculator protects.
A16: Monthly surplus | B16: =B5-B13 -> 8000 | C16: Income left after normal commitments.
A17: Safe spending money now | B17: =MAX(0,B4-B15-B12) -> 0 | C17: Current balance minus buffer and upcoming unavoidable cost.
A18: Next salary date | B18: =IF(DAY(B3)<B6,DATE(YEAR(B3),MONTH(B3),MIN(B6,28)),EDATE(DATE(YEAR(B3),MONTH(B3),MIN(B6,28)),1)) -> 46327 | C18: Used to estimate when a purchase becomes affordable.
A20: YOUR SAFE-ZONE TARGET
A21: Minimum balance for safe zone | B21: =B15 -> 0 | C21: Changes automatically when you edit the buffer months in B14.
A22: Money needed to enter safe zone | B22: =MAX(0,B15+B12-B4) -> 0 | C22: How much more cash you need before optional spending is considered safe.
A23: Current safe-zone status | B23: =IF(B22=0,"IN SAFE ZONE","NEED ₹"&TEXT(B22,"#,##0.00")&" MORE") -> IN SAFE ZONE | C23: Based on your current balance, buffer target, and unavoidable upcoming costs.
A24: Months until safe zone | B24: =IF(B22=0,0,IF(B16<=0,"N/A",ROUNDUP(B22/B16,0))) -> 0 | C24: Number of monthly surpluses needed to reach the buffer target.
A25: Estimated safe-zone date | B25: =IF(B22=0,B3,IF(B16<=0,"",EDATE(B18,B24-1))) -> 46302 | C25: First salary date when your projected balance reaches the safety buffer.
A26: Safe spending money now | B26: =B17 -> 0 | C26: Amount available for an optional purchase without breaking the buffer.

Sheet Compare Items
A1: COMPARE ITEMS
A2: Type only the item and price in the yellow cells. The sheet includes your safety-buffer shortage before calculating the purchase date.
A3: Item | B3: Price | C3: Total Cash Needed | D3: Money Still Needed | E3: Wait (Months) | F3: Earliest Safe Date | G3: Result
C4: =IF(B4="","",'My Budget'!$B$15+'My Budget'!$B$12+B4) | D4: =IF(B4="","",MAX(0,C4-'My Budget'!$B$4)) | E4: =IF(B4="","",IF(B4<='My Budget'!$B$17,0,IF('My Budget'!$B$16<=0,"N/A",ROUNDUP(D4/'My Budget'!$B$16,0)))) | F4: =IF(B4="","",IF(B4<='My Budget'!$B$17,'My Budget'!$B$3,IF('My Budget'!$B$16<=0,"",EDATE('My Budget'!$B$18,E4-1)))) | G4: =IF(B4="","",IF(B4<='My Budget'!$B$17,"BUY NOW",IF('My Budget'!$B$16<=0,"NOT AFFORDABLE","WAIT UNTIL "&TEXT(F4,"dd-mmm-yyyy"))))
C5: =IF(B5="","",'My Budget'!$B$15+'My Budget'!$B$12+B5) | D5: =IF(B5="","",MAX(0,C5-'My Budget'!$B$4)) | E5: =IF(B5="","",IF(B5<='My Budget'!$B$17,0,IF('My Budget'!$B$16<=0,"N/A",ROUNDUP(D5/'My Budget'!$B$16,0)))) | F5: =IF(B5="","",IF(B5<='My Budget'!$B$17,'My Budget'!$B$3,IF('My Budget'!$B$16<=0,"",EDATE('My Budget'!$B$18,E5-1)))) | G5: =IF(B5="","",IF(B5<='My Budget'!$B$17,"BUY NOW",IF('My Budget'!$B$16<=0,"NOT AFFORDABLE","WAIT UNTIL "&TEXT(F5,"dd-mmm-yyyy"))))
C6: =IF(B6="","",'My Budget'!$B$15+'My Budget'!$B$12+B6) | D6: =IF(B6="","",MAX(0,C6-'My Budget'!$B$4)) | E6: =IF(B6="","",IF(B6<='My Budget'!$B$17,0,IF('My Budget'!$B$16<=0,"N/A",ROUNDUP(D6/'My Budget'!$B$16,0)))) | F6: =IF(B6="","",IF(B6<='My Budget'!$B$17,'My Budget'!$B$3,IF('My Budget'!$B$16<=0,"",EDATE('My Budget'!$B$18,E6-1)))) | G6: =IF(B6="","",IF(B6<='My Budget'!$B$17,"BUY NOW",IF('My Budget'!$B$16<=0,"NOT AFFORDABLE","WAIT UNTIL "&TEXT(F6,"dd-mmm-yyyy"))))
C7: =IF(B7="","",'My Budget'!$B$15+'My Budget'!$B$12+B7) | D7: =IF(B7="","",MAX(0,C7-'My Budget'!$B$4)) | E7: =IF(B7="","",IF(B7<='My Budget'!$B$17,0,IF('My Budget'!$B$16<=0,"N/A",ROUNDUP(D7/'My Budget'!$B$16,0)))) | F7: =IF(B7="","",IF(B7<='My Budget'!$B$17,'My Budget'!$B$3,IF('My Budget'!$B$16<=0,"",EDATE('My Budget'!$B$18,E7-1)))) | G7: =IF(B7="","",IF(B7<='My Budget'!$B$17,"BUY NOW",IF('My Budget'!$B$16<=0,"NOT AFFORDABLE","WAIT UNTIL "&TEXT(F7,"dd-mmm-yyyy"))))
C8: =IF(B8="","",'My Budget'!$B$15+'My Budget'!$B$12+B8) | D8: =IF(B8="","",MAX(0,C8-'My Budget'!$B$4)) | E8: =IF(B8="","",IF(B8<='My Budget'!$B$17,0,IF('My Budget'!$B$16<=0,"N/A",ROUNDUP(D8/'My Budget'!$B$16,0)))) | F8: =IF(B8="","",IF(B8<='My Budget'!$B$17,'My Budget'!$B$3,IF('My Budget'!$B$16<=0,"",EDATE('My Budget'!$B$18,E8-1)))) | G8: =IF(B8="","",IF(B8<='My Budget'!$B$17,"BUY NOW",IF('My Budget'!$B$16<=0,"NOT AFFORDABLE","WAIT UNTIL "&TEXT(F8,"dd-mmm-yyyy"))))
C9: =IF(B9="","",'My Budget'!$B$15+'My Budget'!$B$12+B9) | D9: =IF(B9="","",MAX(0,C9-'My Budget'!$B$4)) | E9: =IF(B9="","",IF(B9<='My Budget'!$B$17,0,IF('My Budget'!$B$16<=0,"N/A",ROUNDUP(D9/'My Budget'!$B$16,0)))) | F9: =IF(B9="","",IF(B9<='My Budget'!$B$17,'My Budget'!$B$3,IF('My Budget'!$B$16<=0,"",EDATE('My Budget'!$B$18,E9-1)))) | G9: =IF(B9="","",IF(B9<='My Budget'!$B$17,"BUY NOW",IF('My Budget'!$B$16<=0,"NOT AFFORDABLE","WAIT UNTIL "&TEXT(F9,"dd-mmm-yyyy"))))
C10: =IF(B10="","",'My Budget'!$B$15+'My Budget'!$B$12+B10) | D10: =IF(B10="","",MAX(0,C10-'My Budget'!$B$4)) | E10: =IF(B10="","",IF(B10<='My Budget'!$B$17,0,IF('My Budget'!$B$16<=0,"N/A",ROUNDUP(D10/'My Budget'!$B$16,0)))) | F10: =IF(B10="","",IF(B10<='My Budget'!$B$17,'My Budget'!$B$3,IF('My Budget'!$B$16<=0,"",EDATE('My Budget'!$B$18,E10-1)))) | G10: =IF(B10="","",IF(B10<='My Budget'!$B$17,"BUY NOW",IF('My Budget'!$B$16<=0,"NOT AFFORDABLE","WAIT UNTIL "&TEXT(F10,"dd-mmm-yyyy"))))
C11: =IF(B11="","",'My Budget'!$B$15+'My Budget'!$B$12+B11) | D11: =IF(B11="","",MAX(0,C11-'My Budget'!$B$4)) | E11: =IF(B11="","",IF(B11<='My Budget'!$B$17,0,IF('My Budget'!$B$16<=0,"N/A",ROUNDUP(D11/'My Budget'!$B$16,0)))) | F11: =IF(B11="","",IF(B11<='My Budget'!$B$17,'My Budget'!$B$3,IF('My Budget'!$B$16<=0,"",EDATE('My Budget'!$B$18,E11-1)))) | G11: =IF(B11="","",IF(B11<='My Budget'!$B$17,"BUY NOW",IF('My Budget'!$B$16<=0,"NOT AFFORDABLE","WAIT UNTIL "&TEXT(F11,"dd-mmm-yyyy"))))
C12: =IF(B12="","",'My Budget'!$B$15+'My Budget'!$B$12+B12) | D12: =IF(B12="","",MAX(0,C12-'My Budget'!$B$4)) | E12: =IF(B12="","",IF(B12<='My Budget'!$B$17,0,IF('My Budget'!$B$16<=0,"N/A",ROUNDUP(D12/'My Budget'!$B$16,0)))) | F12: =IF(B12="","",IF(B12<='My Budget'!$B$17,'My Budget'!$B$3,IF('My Budget'!$B$16<=0,"",EDATE('My Budget'!$B$18,E12-1)))) | G12: =IF(B12="","",IF(B12<='My Budget'!$B$17,"BUY NOW",IF('My Budget'!$B$16<=0,"NOT AFFORDABLE","WAIT UNTIL "&TEXT(F12,"dd-mmm-yyyy"))))
C13: =IF(B13="","",'My Budget'!$B$15+'My Budget'!$B$12+B13) | D13: =IF(B13="","",MAX(0,C13-'My Budget'!$B$4)) | E13: =IF(B13="","",IF(B13<='My Budget'!$B$17,0,IF('My Budget'!$B$16<=0,"N/A",ROUNDUP(D13/'My Budget'!$B$16,0)))) | F13: =IF(B13="","",IF(B13<='My Budget'!$B$17,'My Budget'!$B$3,IF('My Budget'!$B$16<=0,"",EDATE('My Budget'!$B$18,E13-1)))) | G13: =IF(B13="","",IF(B13<='My Budget'!$B$17,"BUY NOW",IF('My Budget'!$B$16<=0,"NOT AFFORDABLE","WAIT UNTIL "&TEXT(F13,"dd-mmm-yyyy"))))
C14: =IF(B14="","",'My Budget'!$B$15+'My Budget'!$B$12+B14) | D14: =IF(B14="","",MAX(0,C14-'My Budget'!$B$4)) | E14: =IF(B14="","",IF(B14<='My Budget'!$B$17,0,IF('My Budget'!$B$16<=0,"N/A",ROUNDUP(D14/'My Budget'!$B$16,0)))) | F14: =IF(B14="","",IF(B14<='My Budget'!$B$17,'My Budget'!$B$3,IF('My Budget'!$B$16<=0,"",EDATE('My Budget'!$B$18,E14-1)))) | G14: =IF(B14="","",IF(B14<='My Budget'!$B$17,"BUY NOW",IF('My Budget'!$B$16<=0,"NOT AFFORDABLE","WAIT UNTIL "&TEXT(F14,"dd-mmm-yyyy"))))
C15: =IF(B15="","",'My Budget'!$B$15+'My Budget'!$B$12+B15) | D15: =IF(B15="","",MAX(0,C15-'My Budget'!$B$4)) | E15: =IF(B15="","",IF(B15<='My Budget'!$B$17,0,IF('My Budget'!$B$16<=0,"N/A",ROUNDUP(D15/'My Budget'!$B$16,0)))) | F15: =IF(B15="","",IF(B15<='My Budget'!$B$17,'My Budget'!$B$3,IF('My Budget'!$B$16<=0,"",EDATE('My Budget'!$B$18,E15-1)))) | G15: =IF(B15="","",IF(B15<='My Budget'!$B$17,"BUY NOW",IF('My Budget'!$B$16<=0,"NOT AFFORDABLE","WAIT UNTIL "&TEXT(F15,"dd-mmm-yyyy"))))
... C23: =IF(B23="","",'My Budget'!$B$15+'My Budget'!$B$12+B23) | D23: =IF(B23="","",MAX(0,C23-'My Budget'!$B$4)) | E23: =IF(B23="","",IF(B23<='My Budget'!$B$17,0,IF('My Budget'!$B$16<=0,"N/A",ROUNDUP(D23/'My Budget'!$B$16,0)))) | F23: =IF(B23="","",IF(B23<='My Budget'!$B$17,'My Budget'!$B$3,IF('My Budget'!$B$16<=0,"",EDATE('My Budget'!$B$18,E23-1)))) | G23: =IF(B23="","",IF(B23<='My Budget'!$B$17,"BUY NOW",IF('My Budget'!$B$16<=0,"NOT AFFORDABLE","WAIT UNTIL "&TEXT(F23,"dd-mmm-yyyy"))))

Sheet How It Works
A1: HOW TO USE THIS WORKBOOK
A3: 1 | B3: Update your budget | C3: Open “My Budget” and update the yellow cells, especially your current balance and any unavoidable upcoming cost.
A4: 2 | B4: Check one item | C4: Open “Quick Check”, enter the item name and full price. It shows both the date you reach the safe zone and the later date when the item becomes safe to buy.
A5: 3 | B5: Compare several items | C5: Use “Compare Items”. Enter only an item name and price in yellow cells; every other column is calculated automatically.
A6: 4 | B6: Meaning of safe | C6: Safe means cash-only and keeping your chosen buffer untouched. The current default is 6 months; edit the yellow “Safety buffer (months)” cell B14 in “My Budget” whenever you want.
A7: 5 | B7: Your present baseline | C7: Income ₹8,000; commitments ₹3,400 (loan ₹1,000 + investment ₹400 + petrol ₹2,000); estimated monthly surplus ₹4,600. With a 6-month buffer, the safe-zone minimum is ₹20,400.
A8: 6 | B8: Important assumption | C8: The date estimate assumes income and expenses stay stable. Update the sheet if your balance, petrol use, loan, or salary changes.
B11: Financial note | C11: This is a planning tool, not professional financial advice. It deliberately uses a conservative safety-buffer rule.
